libreflow_launcher
