Metadata-Version: 2.4
Name: libreflow_launcher
Version: 1.3.2
Summary: Launcher for instances of Libreflow asset-manager
Home-page: https://gitlab.com/lfs.coop/libreflow/libreflow_launcher
Author: Valentin Braem
Author-email: valentin.braem@les-fees-speciales.coop
License: LGPLv3+
Keywords: kabaret kitsu gazu animation pipeline libreflow launcher lfs overseer asset-manager
Classifier: Programming Language :: Python :: 3
Classifier: Intended Audience :: Developers
Classifier: License :: OSI Approved :: GNU Lesser General Public License v3 or later (LGPLv3+)
Classifier: Operating System :: OS Independent
Requires-Python: >=3.7
Requires-Dist: pyside6
Requires-Dist: qtpy
Requires-Dist: poetry
Requires-Dist: requests
Requires-Dist: uv
Requires-Dist: toml
Dynamic: author
Dynamic: author-email
Dynamic: classifier
Dynamic: description
Dynamic: description-content-type
Dynamic: home-page
Dynamic: keywords
Dynamic: license
Dynamic: requires-dist
Dynamic: requires-python
Dynamic: summary
